{"dataResult":{"classesCount":2,"itemsCount":81,"dataURL":"file:\/\/\/Users\/amy.wu\/Documents\/gutss\/CreateML\/sharkdissectionclassification\/pplvssharks\/training%20data\/","dataAnalysis":{"issues":[{"severity":"debug","description":"2 classes found, including sharks, ppl"},{"severity":"good","description":"81 images found, automatically creating validation set"},{"description":"Smallest class is \"ppl\" with 35 images","severity":"debug"},{"description":"Largest class is \"sharks\" with 46 images","severity":"debug"}],"classifierAnalysis":{"labelStats":{"sharks":46,"ppl":35}},"summary":{"canUseValidation":1,"sampleCount":81,"classCount":2}},"dataSourceID":"9279043C-23A1-4160-A618-578F8FF43374","createdDate":"2024-02-09T06:19:11Z"},"title":"training data","activityEntities":["dataSourceTrainingStarted",[{"createdDate":"2024-02-09T06:19:24Z","title":"Used By","subtitle":"MyImageClassifier 1 copy","id":"63AFFF36-A522-432A-B25E-8CAC4BF1A50C","event":"dataSourceTrainingStarted"},{"event":"dataSourceTrainingStarted","createdDate":"2024-02-09T06:21:43Z","id":"2FECCA8F-7B4A-4D91-9C43-813FF34AF8D7","subtitle":"MyImageClassifier 1 copy 1","title":"Used By"}],"dataSourceMetrics",[{"subtitle":"2 Classes, 81 Items","title":"Data Summary","event":"dataSourceMetrics","id":"0B567B1C-2475-4E1D-BD1E-557F837912F0","createdDate":"2024-02-09T06:19:24Z"},{"createdDate":"2024-02-09T06:21:43Z","title":"Data Summary","id":"1DC82EE7-5EB1-4D40-A784-208ECFE2590D","event":"dataSourceMetrics","subtitle":"2 Classes, 81 Items"}],"dataSourceCreated",[{"event":"dataSourceCreated","subtitle":"training data","id":"B2BF4D08-F152-4C5E-97AE-AEDE27F1D0A8","createdDate":"2024-02-09T06:19:11Z","title":"Data Source Created"}]],"pathType":0,"createdDate":"2024-02-09T06:19:11Z","id":"9279043C-23A1-4160-A618-578F8FF43374","dataURL":"file:\/\/\/Users\/amy.wu\/Documents\/gutss\/CreateML\/sharkdissectionclassification\/pplvssharks\/training%20data\/","modifiedDate":"2024-02-09T06:21:43Z","version":"1.0","preferredFilename":"training data","dataPathRelativeToProjectURL":"..\/pplvssharks\/training%20data\/","experimentIDs":["5F1C2B2E-2F3F-4F65-8022-B293F7204719","2AB0161D-5CA1-4467-B573-512178D1D3FF"]}